penndraw/__init__.py
penndraw/penndraw.py
penndraw/pyglet_logo.jpg
penndraw/pyglet_logo.png
penndraw/selfie.jpeg
penndraw/unfilled_shapes.py
tests/__init__.py
tests/all_text.py
tests/arcs.py
tests/basic_animation.py
tests/basic_key.py
tests/basic_mouse.py
tests/basic_picture.py
tests/basic_text.py
tests/cascading_square.py
tests/circle.py
tests/clear_then_draw.py
tests/clear_to_white.py
tests/click_counter.py
tests/colored_ellipses.py
tests/colored_filled_ellipses.py
tests/complex_pictures.py
tests/ellipses.py
tests/empty_spikygon.py
tests/ghost.py
tests/gradient.py
tests/light_switch.py
tests/line.py
tests/many_circles.py
tests/many_points.py
tests/mirror_circle.py
tests/named_colors.py
tests/pies.py
tests/pyglet_mode.py
tests/pyglet_test.py
tests/rotate_ellipse.py
tests/rotate_rectangle.py
tests/run_all_tests.py
tests/slow_animation.py
tests/spikygon.py
tests/squares_and_rects.py
tests/squares_and_rects_thickness.py
tests/star_of_lines.py
tests/star_of_lines_variable_thickness.py
tests/unittests.py
tests/window.py
penndraw-0.1.8.dist-info/LICENSE
penndraw-0.1.8.dist-info/METADATA
penndraw-0.1.8.dist-info/WHEEL
penndraw-0.1.8.dist-info/top_level.txt
penndraw-0.1.8.dist-info/RECORD
