Metadata-Version: 2.1
Name: penndraw
Version: 0.1.8
Summary: Drawing library for use at University of Pennsylvania (adapted from Princeton's StdDraw)
Home-page: https://github.com/cis110/PennDraw/
Author: Harry Smith
Author-email: sharry@seas.upenn.edu
Classifier: Development Status :: 3 - Alpha
Classifier: Intended Audience :: Education
Classifier: License :: OSI Approved :: MIT License
Classifier: Programming Language :: Python :: 3
Classifier: Programming Language :: Python :: 3.10
Classifier: Programming Language :: Python :: 3.11
Classifier: Programming Language :: Python :: 3.12
Requires-Python: >=3.10
License-File: LICENSE
Requires-Dist: multipledispatch (==1.0.0)
Requires-Dist: mypy (==1.9.0)
Requires-Dist: mypy-extensions (==1.0.0)
Requires-Dist: pyglet (==2.0.14)
Requires-Dist: tomli (==2.0.1)
Requires-Dist: typing-extensions (==4.10.0)
